<?xml version="1.0" encoding="UTF-8"?>
<!DOCTYPE xdrs-output SYSTEM "src/data/boxer/xdrs.dtd">
<xdrs-output version="boxer v2109 (unix build on 16 januari 2012, 15:20:04)">
<!-- The bestselling book Midnight in the Garden of Good and Evil is based on a true story of murder in the southern city of Savannah , Georgia . Hollywood turned it into a movie - making the crime 's location , a historic building known as Mercer House , a major tourist attraction . For producer Roger Hsu , Elaine Lu has more on the house and the story that captivated the city . --> 

<xdrs xml:id="1">
 <words>
  <word xml:id="i1001">The</word>
  <word xml:id="i1002">bestselling</word>
  <word xml:id="i1003">book</word>
  <word xml:id="i1004">Midnight</word>
  <word xml:id="i1005">in</word>
  <word xml:id="i1006">the</word>
  <word xml:id="i1007">Garden</word>
  <word xml:id="i1008">of</word>
  <word xml:id="i1009">Good</word>
  <word xml:id="i1010">and</word>
  <word xml:id="i1011">Evil</word>
  <word xml:id="i1012">is</word>
  <word xml:id="i1013">based</word>
  <word xml:id="i1014">on</word>
  <word xml:id="i1015">a</word>
  <word xml:id="i1016">true</word>
  <word xml:id="i1017">story</word>
  <word xml:id="i1018">of</word>
  <word xml:id="i1019">murder</word>
  <word xml:id="i1020">in</word>
  <word xml:id="i1021">the</word>
  <word xml:id="i1022">southern</word>
  <word xml:id="i1023">city</word>
  <word xml:id="i1024">of</word>
  <word xml:id="i1025">Savannah</word>
  <word xml:id="i1026">,</word>
  <word xml:id="i1027">Georgia</word>
  <word xml:id="i1028">.</word>
  <word xml:id="i2001">Hollywood</word>
  <word xml:id="i2002">turned</word>
  <word xml:id="i2003">it</word>
  <word xml:id="i2004">into</word>
  <word xml:id="i2005">a</word>
  <word xml:id="i2006">movie</word>
  <word xml:id="i2007">-</word>
  <word xml:id="i2008">making</word>
  <word xml:id="i2009">the</word>
  <word xml:id="i2010">crime</word>
  <word xml:id="i2011">'s</word>
  <word xml:id="i2012">location</word>
  <word xml:id="i2013">,</word>
  <word xml:id="i2014">a</word>
  <word xml:id="i2015">historic</word>
  <word xml:id="i2016">building</word>
  <word xml:id="i2017">known</word>
  <word xml:id="i2018">as</word>
  <word xml:id="i2019">Mercer</word>
  <word xml:id="i2020">House</word>
  <word xml:id="i2021">,</word>
  <word xml:id="i2022">a</word>
  <word xml:id="i2023">major</word>
  <word xml:id="i2024">tourist</word>
  <word xml:id="i2025">attraction</word>
  <word xml:id="i2026">.</word>
  <word xml:id="i3001">For</word>
  <word xml:id="i3002">producer</word>
  <word xml:id="i3003">Roger</word>
  <word xml:id="i3004">Hsu</word>
  <word xml:id="i3005">,</word>
  <word xml:id="i3006">Elaine</word>
  <word xml:id="i3007">Lu</word>
  <word xml:id="i3008">has</word>
  <word xml:id="i3009">more</word>
  <word xml:id="i3010">on</word>
  <word xml:id="i3011">the</word>
  <word xml:id="i3012">house</word>
  <word xml:id="i3013">and</word>
  <word xml:id="i3014">the</word>
  <word xml:id="i3015">story</word>
  <word xml:id="i3016">that</word>
  <word xml:id="i3017">captivated</word>
  <word xml:id="i3018">the</word>
  <word xml:id="i3019">city</word>
  <word xml:id="i3020">.</word>
 </words>
 <postags>
  <tag type="pos" index="i1001">DT</tag>
  <tag type="pos" index="i1002">VBG</tag>
  <tag type="pos" index="i1003">NN</tag>
  <tag type="pos" index="i1004">NN</tag>
  <tag type="pos" index="i1005">IN</tag>
  <tag type="pos" index="i1006">DT</tag>
  <tag type="pos" index="i1007">NNP</tag>
  <tag type="pos" index="i1008">IN</tag>
  <tag type="pos" index="i1009">NNP</tag>
  <tag type="pos" index="i1010">CC</tag>
  <tag type="pos" index="i1011">NNP</tag>
  <tag type="pos" index="i1012">VBZ</tag>
  <tag type="pos" index="i1013">VBN</tag>
  <tag type="pos" index="i1014">IN</tag>
  <tag type="pos" index="i1015">DT</tag>
  <tag type="pos" index="i1016">JJ</tag>
  <tag type="pos" index="i1017">NN</tag>
  <tag type="pos" index="i1018">IN</tag>
  <tag type="pos" index="i1019">NN</tag>
  <tag type="pos" index="i1020">IN</tag>
  <tag type="pos" index="i1021">DT</tag>
  <tag type="pos" index="i1022">JJ</tag>
  <tag type="pos" index="i1023">NN</tag>
  <tag type="pos" index="i1024">IN</tag>
  <tag type="pos" index="i1025">NNP</tag>
  <tag type="pos" index="i1026">,</tag>
  <tag type="pos" index="i1027">NNP</tag>
  <tag type="pos" index="i1028">.</tag>
  <tag type="pos" index="i2001">NNP</tag>
  <tag type="pos" index="i2002">VBD</tag>
  <tag type="pos" index="i2003">PRP</tag>
  <tag type="pos" index="i2004">IN</tag>
  <tag type="pos" index="i2005">DT</tag>
  <tag type="pos" index="i2006">NN</tag>
  <tag type="pos" index="i2007">IN</tag>
  <tag type="pos" index="i2008">VBG</tag>
  <tag type="pos" index="i2009">DT</tag>
  <tag type="pos" index="i2010">NN</tag>
  <tag type="pos" index="i2011">POS</tag>
  <tag type="pos" index="i2012">NN</tag>
  <tag type="pos" index="i2013">,</tag>
  <tag type="pos" index="i2014">DT</tag>
  <tag type="pos" index="i2015">JJ</tag>
  <tag type="pos" index="i2016">NN</tag>
  <tag type="pos" index="i2017">VBN</tag>
  <tag type="pos" index="i2018">IN</tag>
  <tag type="pos" index="i2019">NNP</tag>
  <tag type="pos" index="i2020">NNP</tag>
  <tag type="pos" index="i2021">,</tag>
  <tag type="pos" index="i2022">DT</tag>
  <tag type="pos" index="i2023">JJ</tag>
  <tag type="pos" index="i2024">NN</tag>
  <tag type="pos" index="i2025">NN</tag>
  <tag type="pos" index="i2026">.</tag>
  <tag type="pos" index="i3001">IN</tag>
  <tag type="pos" index="i3002">NN</tag>
  <tag type="pos" index="i3003">NNP</tag>
  <tag type="pos" index="i3004">NNP</tag>
  <tag type="pos" index="i3005">,</tag>
  <tag type="pos" index="i3006">NNP</tag>
  <tag type="pos" index="i3007">NNP</tag>
  <tag type="pos" index="i3008">VBZ</tag>
  <tag type="pos" index="i3009">RBR</tag>
  <tag type="pos" index="i3010">IN</tag>
  <tag type="pos" index="i3011">DT</tag>
  <tag type="pos" index="i3012">NN</tag>
  <tag type="pos" index="i3013">CC</tag>
  <tag type="pos" index="i3014">DT</tag>
  <tag type="pos" index="i3015">NN</tag>
  <tag type="pos" index="i3016">WDT</tag>
  <tag type="pos" index="i3017">VBD</tag>
  <tag type="pos" index="i3018">DT</tag>
  <tag type="pos" index="i3019">NN</tag>
  <tag type="pos" index="i3020">.</tag>
 </postags>
 <netags>
  <tag type="ne" index="i1006">I-DAT</tag>
  <tag type="ne" index="i1007">I-DAT</tag>
  <tag type="ne" index="i1008">I-DAT</tag>
  <tag type="ne" index="i1009">I-DAT</tag>
  <tag type="ne" index="i1011">I-ORG</tag>
  <tag type="ne" index="i1025">I-LOC</tag>
  <tag type="ne" index="i1027">I-LOC</tag>
  <tag type="ne" index="i2001">I-PER</tag>
  <tag type="ne" index="i2019">I-ORG</tag>
  <tag type="ne" index="i2020">I-ORG</tag>
  <tag type="ne" index="i3003">I-PER</tag>
  <tag type="ne" index="i3004">I-PER</tag>
  <tag type="ne" index="i3006">I-PER</tag>
  <tag type="ne" index="i3007">I-PER</tag>
 </netags>
 <sdrs>
  <constituents>
  <sub>
  <constituent label="k0">
  <drs type="sentence">
   <tokens>
    <token>The</token>
    <token>bestselling</token>
    <token>book</token>
    <token>Midnight</token>
    <token>the</token>
    <token>Garden</token>
    <token>Good</token>
    <token>Evil</token>
    <token>the</token>
    <token>southern</token>
    <token>city</token>
    <token>Savannah</token>
    <token>Georgia</token>
    <token>Hollywood</token>
    <token>the</token>
    <token>crime</token>
    <token>'s</token>
    <token>location</token>
    <token>Mercer</token>
    <token>House</token>
    <token>producer</token>
    <token>Roger</token>
    <token>Hsu</token>
    <token>Elaine</token>
    <token>Lu</token>
    <token>the</token>
    <token>house</token>
   </tokens>
   <dom>
    <dr name="t1">
    <indexlist>
    </indexlist>
    </dr>
    <dr name="x2">
    <indexlist>
    </indexlist>
    </dr>
    <dr name="x3">
    <indexlist>
    <index pos="1">i1001</index>
    </indexlist>
    </dr>
    <dr name="e4">
    <indexlist>
    </indexlist>
    </dr>
    <dr name="x5">
    <indexlist>
    <index pos="6">i1006</index>
    </indexlist>
    </dr>
    <dr name="x6">
    <indexlist>
    </indexlist>
    </dr>
    <dr name="x7">
    <indexlist>
    <index pos="21">i1021</index>
    </indexlist>
    </dr>
    <dr name="x8">
    <indexlist>
    </indexlist>
    </dr>
    <dr name="x9">
    <indexlist>
    </indexlist>
    </dr>
    <dr name="x10">
    <indexlist>
    </indexlist>
    </dr>
    <dr name="x11">
    <indexlist>
    </indexlist>
    </dr>
    <dr name="x12">
    <indexlist>
    <index pos="9">i2009</index>
    </indexlist>
    </dr>
    <dr name="x13">
    <indexlist>
    </indexlist>
    </dr>
    <dr name="x14">
    <indexlist>
    </indexlist>
    </dr>
    <dr name="x15">
    <indexlist>
    </indexlist>
    </dr>
    <dr name="x16">
    <indexlist>
    <index pos="11">i3011</index>
    </indexlist>
    </dr>
    <dr name="x17">
    <indexlist>
    </indexlist>
    </dr>
    <dr name="x18">
    <indexlist>
    </indexlist>
    </dr>
    <dr name="x19">
    <indexlist>
    </indexlist>
    </dr>
    <dr name="x20">
    <indexlist>
    </indexlist>
    </dr>
   </dom>
   <con>
    <pred arg="x7" symbol="city" type="n" sense="0">
    <indexlist>
    <index pos="23">i1023</index>
    </indexlist>
    </pred>
    <pred arg="t1" symbol="now" type="a" sense="1">
    <indexlist>
    </indexlist>
    </pred>
    <pred arg="x8" symbol="neuter" type="a" sense="0">
    <indexlist>
    </indexlist>
    </pred>
    <named arg="x9" symbol="georgia" type="loc">
    <indexlist>
    <index pos="27">i1027</index>
    </indexlist>
    </named>
    <named arg="x8" symbol="savannah" type="loc">
    <indexlist>
    <index pos="25">i1025</index>
    </indexlist>
    </named>
    <pred arg="x7" symbol="southern" type="a" sense="0">
    <indexlist>
    <index pos="22">i1022</index>
    </indexlist>
    </pred>
    <pred arg="e4" symbol="bestsell" type="v" sense="0">
    <indexlist>
    <index pos="2">i1002</index>
    </indexlist>
    </pred>
    <pred arg="x2" symbol="book" type="n" sense="0">
    <indexlist>
    <index pos="3">i1003</index>
    </indexlist>
    </pred>
    <rel arg1="x2" arg2="x3" symbol="nn" sense="0">
    <indexlist>
    </indexlist>
    </rel>
    <pred arg="x3" symbol="midnight" type="n" sense="0">
    <indexlist>
    <index pos="4">i1004</index>
    </indexlist>
    </pred>
    <rel arg1="e4" arg2="x3" symbol="agent" sense="0">
    <indexlist>
    </indexlist>
    </rel>
    <named arg="x5" symbol="garden" type="nam">
    <indexlist>
    <index pos="7">i1007</index>
    </indexlist>
    </named>
    <named arg="x6" symbol="good" type="nam">
    <indexlist>
    <index pos="9">i1009</index>
    </indexlist>
    </named>
    <named arg="x10" symbol="evil" type="org">
    <indexlist>
    <index pos="11">i1011</index>
    </indexlist>
    </named>
    <named arg="x11" symbol="hollywood" type="per">
    <indexlist>
    <index pos="1">i2001</index>
    </indexlist>
    </named>
    <pred arg="x12" symbol="crime" type="n" sense="0">
    <indexlist>
    <index pos="10">i2010</index>
    </indexlist>
    </pred>
    <pred arg="x13" symbol="location" type="n" sense="0">
    <indexlist>
    <index pos="12">i2012</index>
    </indexlist>
    </pred>
    <rel arg1="x13" arg2="x12" symbol="of" sense="0">
    <indexlist>
    <index pos="11">i2011</index>
    </indexlist>
    </rel>
    <named arg="x14" symbol="mercer_house" type="org">
    <indexlist>
    <index pos="19">i2019</index>
    <index pos="20">i2020</index>
    </indexlist>
    </named>
    <named arg="x15" symbol="elaine" type="per">
    <indexlist>
    <index pos="6">i3006</index>
    </indexlist>
    </named>
    <named arg="x15" symbol="lu" type="per">
    <indexlist>
    <index pos="7">i3007</index>
    </indexlist>
    </named>
    <pred arg="x16" symbol="house" type="n" sense="0">
    <indexlist>
    <index pos="12">i3012</index>
    </indexlist>
    </pred>
    <named arg="x18" symbol="roger" type="per">
    <indexlist>
    <index pos="3">i3003</index>
    </indexlist>
    </named>
    <named arg="x18" symbol="hsu" type="per">
    <indexlist>
    <index pos="4">i3004</index>
    </indexlist>
    </named>
    <rel arg1="x17" arg2="x18" symbol="nn" sense="0">
    <indexlist>
    </indexlist>
    </rel>
    <pred arg="x17" symbol="producer" type="n" sense="0">
    <indexlist>
    <index pos="2">i3002</index>
    </indexlist>
    </pred>
    <named arg="x20" symbol="roger" type="per">
    <indexlist>
    <index pos="3">i3003</index>
    </indexlist>
    </named>
    <named arg="x20" symbol="hsu" type="per">
    <indexlist>
    <index pos="4">i3004</index>
    </indexlist>
    </named>
    <rel arg1="x19" arg2="x20" symbol="nn" sense="0">
    <indexlist>
    </indexlist>
    </rel>
    <pred arg="x19" symbol="producer" type="n" sense="0">
    <indexlist>
    <index pos="2">i3002</index>
    </indexlist>
    </pred>
   </con>
  </drs>
  </constituent>
  <constituent label="k21">
  <sdrs>
   <constituents>
   <constituent label="k22">
   <drs type="sentence">
    <tokens>
     <token>in</token>
     <token>of</token>
     <token>based</token>
     <token>on</token>
     <token>a</token>
     <token>true</token>
     <token>story</token>
     <token>of</token>
     <token>murder</token>
     <token>in</token>
     <token>of</token>
     <token>,</token>
    </tokens>
    <dom>
     <dr name="e23">
     <indexlist>
     </indexlist>
     </dr>
     <dr name="x24">
     <indexlist>
     <index pos="15">i1015</index>
     </indexlist>
     </dr>
     <dr name="x25">
     <indexlist>
     </indexlist>
     </dr>
     <dr name="t26">
     <indexlist>
     </indexlist>
     </dr>
     <dr name="e27">
     <indexlist>
     </indexlist>
     </dr>
     <dr name="x28">
     <indexlist>
     <index pos="15">i1015</index>
     </indexlist>
     </dr>
     <dr name="x29">
     <indexlist>
     </indexlist>
     </dr>
     <dr name="t30">
     <indexlist>
     </indexlist>
     </dr>
    </dom>
    <con>
     <pred arg="x24" symbol="story" type="n" sense="0">
     <indexlist>
     <index pos="17">i1017</index>
     </indexlist>
     </pred>
     <pred arg="e23" symbol="base" type="v" sense="97010000">
     <indexlist>
     <index pos="13">i1013</index>
     </indexlist>
     </pred>
     <pred arg="x25" symbol="murder" type="n" sense="0">
     <indexlist>
     <index pos="19">i1019</index>
     </indexlist>
     </pred>
     <rel arg1="x5" arg2="x6" symbol="of" sense="0">
     <indexlist>
     <index pos="8">i1008</index>
     </indexlist>
     </rel>
     <rel arg1="x3" arg2="x5" symbol="in" sense="0">
     <indexlist>
     <index pos="5">i1005</index>
     </indexlist>
     </rel>
     <rel arg1="e23" arg2="x3" symbol="Theme1" sense="0">
     <indexlist>
     </indexlist>
     </rel>
     <pred arg="x24" symbol="true" type="a" sense="0">
     <indexlist>
     <index pos="16">i1016</index>
     </indexlist>
     </pred>
     <rel arg1="x8" arg2="x9" symbol="rel" sense="0">
     <indexlist>
     <index pos="26">i1026</index>
     </indexlist>
     </rel>
     <rel arg1="x7" arg2="x8" symbol="of" sense="0">
     <indexlist>
     <index pos="24">i1024</index>
     </indexlist>
     </rel>
     <rel arg1="x25" arg2="x7" symbol="in" sense="0">
     <indexlist>
     <index pos="20">i1020</index>
     </indexlist>
     </rel>
     <rel arg1="x24" arg2="x25" symbol="of" sense="0">
     <indexlist>
     <index pos="18">i1018</index>
     </indexlist>
     </rel>
     <rel arg1="e23" arg2="x24" symbol="Theme2" sense="0">
     <indexlist>
     <index pos="14">i1014</index>
     </indexlist>
     </rel>
     <rel arg1="e23" arg2="t26" symbol="temp_included" sense="1">
     <indexlist>
     </indexlist>
     </rel>
     <eq arg1="t26" arg2="t1">
     <indexlist>
     </indexlist>
     </eq>
     <pred arg="e27" symbol="base" type="v" sense="97010000">
     <indexlist>
     <index pos="13">i1013</index>
     </indexlist>
     </pred>
     <pred arg="x28" symbol="story" type="n" sense="0">
     <indexlist>
     <index pos="17">i1017</index>
     </indexlist>
     </pred>
     <pred arg="x29" symbol="murder" type="n" sense="0">
     <indexlist>
     <index pos="19">i1019</index>
     </indexlist>
     </pred>
     <rel arg1="x3" arg2="x10" symbol="in" sense="0">
     <indexlist>
     <index pos="5">i1005</index>
     </indexlist>
     </rel>
     <rel arg1="e27" arg2="x3" symbol="Theme1" sense="0">
     <indexlist>
     </indexlist>
     </rel>
     <pred arg="x28" symbol="true" type="a" sense="0">
     <indexlist>
     <index pos="16">i1016</index>
     </indexlist>
     </pred>
     <rel arg1="x8" arg2="x9" symbol="rel" sense="0">
     <indexlist>
     <index pos="26">i1026</index>
     </indexlist>
     </rel>
     <rel arg1="x7" arg2="x8" symbol="of" sense="0">
     <indexlist>
     <index pos="24">i1024</index>
     </indexlist>
     </rel>
     <rel arg1="x29" arg2="x7" symbol="in" sense="0">
     <indexlist>
     <index pos="20">i1020</index>
     </indexlist>
     </rel>
     <rel arg1="x28" arg2="x29" symbol="of" sense="0">
     <indexlist>
     <index pos="18">i1018</index>
     </indexlist>
     </rel>
     <rel arg1="e27" arg2="x28" symbol="Theme2" sense="0">
     <indexlist>
     <index pos="14">i1014</index>
     </indexlist>
     </rel>
     <rel arg1="e27" arg2="t30" symbol="temp_included" sense="1">
     <indexlist>
     </indexlist>
     </rel>
     <eq arg1="t30" arg2="t1">
     <indexlist>
     </indexlist>
     </eq>
    </con>
   </drs>
   </constituent>
   <constituent label="k31">
   <drs type="sentence">
    <tokens>
     <token>turned</token>
     <token>into</token>
     <token>a</token>
     <token>movie</token>
     <token>-</token>
     <token>making</token>
     <token>,</token>
     <token>a</token>
     <token>historic</token>
     <token>building</token>
     <token>known</token>
     <token>as</token>
     <token>a</token>
     <token>major</token>
     <token>tourist</token>
     <token>attraction</token>
    </tokens>
    <dom>
     <dr name="e32">
     <indexlist>
     </indexlist>
     </dr>
     <dr name="x33">
     <indexlist>
     <index pos="5">i2005</index>
     </indexlist>
     </dr>
     <dr name="t34">
     <indexlist>
     </indexlist>
     </dr>
     <dr name="x35">
     <indexlist>
     <index pos="14">i2014</index>
     </indexlist>
     </dr>
     <dr name="e36">
     <indexlist>
     </indexlist>
     </dr>
     <dr name="x37">
     <indexlist>
     </indexlist>
     </dr>
     <dr name="x38">
     <indexlist>
     <index pos="22">i2022</index>
     </indexlist>
     </dr>
     <dr name="e39">
     <indexlist>
     </indexlist>
     </dr>
    </dom>
    <con>
     <pred arg="e32" symbol="turn" type="v" sense="51031000">
     <indexlist>
     <index pos="2">i2002</index>
     </indexlist>
     </pred>
     <pred arg="x33" symbol="movie" type="n" sense="0">
     <indexlist>
     <index pos="6">i2006</index>
     </indexlist>
     </pred>
     <rel arg1="e32" arg2="x11" symbol="Agent" sense="0">
     <indexlist>
     </indexlist>
     </rel>
     <rel arg1="e32" arg2="x8" symbol="Theme" sense="0">
     <indexlist>
     </indexlist>
     </rel>
     <rel arg1="e32" arg2="x33" symbol="Oblique" sense="0">
     <indexlist>
     <index pos="4">i2004</index>
     </indexlist>
     </rel>
     <rel arg1="e32" arg2="t34" symbol="temp_included" sense="1">
     <indexlist>
     </indexlist>
     </rel>
     <rel arg1="t34" arg2="t1" symbol="temp_before" sense="1">
     <indexlist>
     </indexlist>
     </rel>
     <pred arg="e36" symbol="know" type="v" sense="29020100">
     <indexlist>
     <index pos="17">i2017</index>
     </indexlist>
     </pred>
     <pred arg="x35" symbol="building" type="n" sense="0">
     <indexlist>
     <index pos="16">i2016</index>
     </indexlist>
     </pred>
     <pred arg="x35" symbol="historic" type="a" sense="0">
     <indexlist>
     <index pos="15">i2015</index>
     </indexlist>
     </pred>
     <rel arg1="e36" arg2="x35" symbol="Theme" sense="0">
     <indexlist>
     </indexlist>
     </rel>
     <pred arg="e39" symbol="make" type="v" sense="29030000">
     <indexlist>
     <index pos="8">i2008</index>
     </indexlist>
     </pred>
     <pred arg="x37" symbol="tourist" type="n" sense="0">
     <indexlist>
     <index pos="24">i2024</index>
     </indexlist>
     </pred>
     <rel arg1="x37" arg2="x38" symbol="nn" sense="0">
     <indexlist>
     </indexlist>
     </rel>
     <pred arg="x38" symbol="attraction" type="n" sense="0">
     <indexlist>
     <index pos="25">i2025</index>
     </indexlist>
     </pred>
     <rel arg1="e36" arg2="x14" symbol="as" sense="0">
     <indexlist>
     <index pos="18">i2018</index>
     </indexlist>
     </rel>
     <pred arg="x38" symbol="major" type="a" sense="0">
     <indexlist>
     <index pos="23">i2023</index>
     </indexlist>
     </pred>
     <rel arg1="e36" arg2="x38" symbol="Predicate" sense="0">
     <indexlist>
     <index pos="18">i2018</index>
     </indexlist>
     </rel>
     <rel arg1="x13" arg2="x35" symbol="rel" sense="0">
     <indexlist>
     <index pos="13">i2013</index>
     </indexlist>
     </rel>
     <rel arg1="e39" arg2="x11" symbol="Agent" sense="0">
     <indexlist>
     </indexlist>
     </rel>
     <rel arg1="e39" arg2="x13" symbol="Theme" sense="0">
     <indexlist>
     </indexlist>
     </rel>
     <rel arg1="e39" arg2="e32" symbol="-" sense="0">
     <indexlist>
     <index pos="7">i2007</index>
     </indexlist>
     </rel>
    </con>
   </drs>
   </constituent>
   <constituent label="k40">
   <drs type="sentence">
    <tokens>
     <token>For</token>
     <token>has</token>
     <token>more</token>
     <token>on</token>
     <token>captivated</token>
    </tokens>
    <dom>
     <dr name="x41">
     <indexlist>
     </indexlist>
     </dr>
     <dr name="e42">
     <indexlist>
     </indexlist>
     </dr>
     <dr name="t43">
     <indexlist>
     </indexlist>
     </dr>
     <dr name="e44">
     <indexlist>
     </indexlist>
     </dr>
     <dr name="t45">
     <indexlist>
     </indexlist>
     </dr>
     <dr name="e46">
     <indexlist>
     </indexlist>
     </dr>
     <dr name="t47">
     <indexlist>
     </indexlist>
     </dr>
    </dom>
    <con>
     <pred arg="x41" symbol="more" type="n" sense="0">
     <indexlist>
     <index pos="9">i3009</index>
     </indexlist>
     </pred>
     <pred arg="e42" symbol="have" type="v" sense="39040100">
     <indexlist>
     <index pos="8">i3008</index>
     </indexlist>
     </pred>
     <rel arg1="x41" arg2="x16" symbol="on" sense="0">
     <indexlist>
     <index pos="10">i3010</index>
     </indexlist>
     </rel>
     <rel arg1="e42" arg2="x15" symbol="Agent" sense="0">
     <indexlist>
     </indexlist>
     </rel>
     <rel arg1="e42" arg2="x41" symbol="Patient" sense="0">
     <indexlist>
     </indexlist>
     </rel>
     <rel arg1="e42" arg2="t43" symbol="temp_included" sense="1">
     <indexlist>
     </indexlist>
     </rel>
     <eq arg1="t43" arg2="t1">
     <indexlist>
     </indexlist>
     </eq>
     <rel arg1="e42" arg2="x18" symbol="for" sense="0">
     <indexlist>
     <index pos="1">i3001</index>
     </indexlist>
     </rel>
     <pred arg="e44" symbol="captivate" type="v" sense="31010000">
     <indexlist>
     <index pos="17">i3017</index>
     </indexlist>
     </pred>
     <pred arg="e46" symbol="have" type="v" sense="39040100">
     <indexlist>
     <index pos="8">i3008</index>
     </indexlist>
     </pred>
     <rel arg1="e44" arg2="x24" symbol="Cause" sense="0">
     <indexlist>
     </indexlist>
     </rel>
     <rel arg1="e44" arg2="x7" symbol="Experiencer" sense="0">
     <indexlist>
     </indexlist>
     </rel>
     <rel arg1="e44" arg2="t45" symbol="temp_included" sense="1">
     <indexlist>
     </indexlist>
     </rel>
     <rel arg1="t45" arg2="t1" symbol="temp_before" sense="1">
     <indexlist>
     </indexlist>
     </rel>
     <rel arg1="e46" arg2="x15" symbol="Agent" sense="0">
     <indexlist>
     </indexlist>
     </rel>
     <rel arg1="e46" arg2="x24" symbol="Patient" sense="0">
     <indexlist>
     </indexlist>
     </rel>
     <rel arg1="e46" arg2="t47" symbol="temp_included" sense="1">
     <indexlist>
     </indexlist>
     </rel>
     <eq arg1="t47" arg2="t1">
     <indexlist>
     </indexlist>
     </eq>
     <rel arg1="e46" arg2="x20" symbol="for" sense="0">
     <indexlist>
     <index pos="1">i3001</index>
     </indexlist>
     </rel>
    </con>
   </drs>
   </constituent>
   </constituents>
   <relations>
   <drel arg1="k31" arg2="k40" sym="continuation">
   <indexlist>
   </indexlist>
   </drel>
   <drel arg1="k22" arg2="k31" sym="continuation">
   <indexlist>
   </indexlist>
   </drel>
   </relations>
  </sdrs>
  </constituent>
  </sub>
  </constituents>
  <relations>
  <drel arg1="k0" arg2="k21" sym="presupposition">
  <indexlist>
  </indexlist>
  </drel>
  </relations>
 </sdrs>
</xdrs>

</xdrs-output>
